LICENSE
MANIFEST.in
README.md
setup.py
django_simple_admin_overlay.egg-info/PKG-INFO
django_simple_admin_overlay.egg-info/SOURCES.txt
django_simple_admin_overlay.egg-info/dependency_links.txt
django_simple_admin_overlay.egg-info/top_level.txt
docs/img/django_simple_admin_overlay_top_closed.png
docs/img/django_simple_admin_overlay_top_open.png
simple_admin_overlay/__init__.py
simple_admin_overlay/apps.py
simple_admin_overlay/middleware.py
simple_admin_overlay/settings.py
simple_admin_overlay/util.py
simple_admin_overlay/static/simple_admin_overlay/css/simple_admin_overlay.css
simple_admin_overlay/static/simple_admin_overlay/img/caret-down-inverse.png
simple_admin_overlay/static/simple_admin_overlay/img/caret-down.png
simple_admin_overlay/static/simple_admin_overlay/img/caret-left-inverse.png
simple_admin_overlay/static/simple_admin_overlay/img/caret-left.png
simple_admin_overlay/static/simple_admin_overlay/img/caret-right-inverse.png
simple_admin_overlay/static/simple_admin_overlay/img/caret-right.png
simple_admin_overlay/static/simple_admin_overlay/img/caret-up-inverse.png
simple_admin_overlay/static/simple_admin_overlay/img/caret-up.png
simple_admin_overlay/static/simple_admin_overlay/js/simple_admin_overlay.js
simple_admin_overlay/templates/simple_admin_overlay.html