Metadata-Version: 1.1
Name: django-simple-admin-overlay
Version: 0.2
Summary: Lightweight Django app which displays simple overlay with admin links on the frontend pages.
Home-page: https://github.com/bonidjukic/django-simple-admin-overlay
Author: Boni Đukić
Author-email: boni@djukic.com.hr
License: MIT License
Platform: UNKNOWN
Classifier: Environment :: Web Environment
Classifier: Framework :: Django
Classifier: Framework :: Django :: 1.10
Classifier: Intended Audience :: Developers
Classifier: License :: OSI Approved :: MIT License
Classifier: Operating System :: OS Independent
Classifier: Programming Language :: Python
Classifier: Programming Language :: Python :: 3.5
Classifier: Topic :: Utilities
